{"cameraMode":{"drawMode":0,"name":"Shaded","section":"Shading Mode"},"sceneLighting":true,"audioPlay":false,"sceneViewState":{"m_AlwaysRefresh":false,"showFog":true,"showSkybox":true,"showFlares":true,"showImageEffects":true,"showParticleSystems":true,"showVisualEffectGraphs":true,"m_FxEnabled":true},"in2DMode":false,"pivot":{"x":0.7668601870536804,"y":1.921595573425293,"z":-0.11090779304504395},"rotation":{"x":0.005999644286930561,"y":0.008102216757833958,"z":-0.00004882662324234843,"w":0.9999480247497559},"size":3.549433946609497,"orthographic":false}